<?xml version="1.0" encoding="iso-8859-1" ?>
<Sheet name="Upper Extremities Angles">
    
<!--
pro/supi    elbowflex   shoulderele
            RElbowFlexExtAngle
            
humabdukdircos  humanteretrodircos  humeruselevationdircos
RHumerusAbdAddDircosAngle       RHumerusElevationDirCos

humerusiroaroglobe  humiroaroconjunct
                    RHumerusIroAroAngle
                    
thoraxtilt  thoraxboliquity thoraxrotation
TrunkTiltAngle   RTrunkObliquityAngle   TrunkRotationAngle

Kippung     Schiefstand     Rotation
-->

  <Pages>
      
    <Page name="Angles" rows="4" columns="3">
        
        <!-- first row -->
         
        <Diagram name="ShoulderAbduktion" 
           column="0"
           row="0"
           xunit="% movement cycle"
           yunit="deg" 
           diagramDescriptionDown="add"
           diagramDescriptionUp="abd" 
           plane="" 
           diagramType="xt" 
           diagramTitle="A  shoulder abd/add">
         <Label name="RShoulderEleDepHDCalDirCosAngle"
              component="0" 
              side="right"/>
         <Label name="LShoulderEleDepHDCalDirCosAngle"
              component="0" 
              side="left"/>       
        </Diagram>
        
        <Diagram name="ShoulderAnteRetroversion" 
           column="1"
           row="0"
           xunit="% movement cycle"
           yunit="deg" 
           diagramDescriptionDown="retro"
           diagramDescriptionUp="ante" 
           plane="" 
           diagramType="xt" 
           diagramTitle="C  shoulder ante/retro">
           <Label name="RShoulderAnteRetroHDCalDirCosAngle"
                  component="0" 
                  side="right"/>
           <Label name="LShoulderAnteRetroHDCalDirCosAngle"
                  component="0" 
                  side="left"/>
        </Diagram>
        
        <Diagram name="ShoulderIroAro" 
           column="2"
           row="0"
           xunit="% movement cycle"
           yunit="deg" 
           diagramDescriptionDown="ext"
           diagramDescriptionUp="int"
           plane="" 
           diagramType="xt" 
           diagramTitle="E  shoulder int/ext rot">
           <Label name="RShoulderIroAroHDCalAngle"
              component="0" 
              side="right"/>
           <Label name="LShoulderIroAroHDCalAngle"
              component="0" 
              side="left"/>        
        </Diagram>
         
        <Diagram name="SGElevation" 
           column="0"
           row="1"
           xunit="% movement cycle"
           yunit="deg" 
           diagramDescriptionDown="dep" 
           diagramDescriptionUp="ele" 
           plane="" 
           diagramType="xt" 
           diagramTitle="B  shoulder girdle ele/dep">
           <Label name="RShoulderGirdleEleDepHDCalAngle"
                  component="0" 
                  side="right"/> 
           <Label name="LShoulderGirdleEleDepHDCalAngle"
                  component="0" 
                  side="left"/>
         </Diagram>
      
         <Diagram name="SGProRetrac" 
                   column="1"
                   row="1"
                   xunit="% movement cycle"
                   yunit="deg" 
                   diagramDescriptionDown="retrac" 
                   diagramDescriptionUp="pro" 
                   plane="" 
                   diagramType="xt" 
                   diagramTitle="D  shoulder girdle pro/retrac">
               <Label name="RShoulderGirdleProRetracHDCalProjAngle"
                    component="0"
                    side="right"/>
               <Label name="LShoulderGirdleProRetracHDCalProjAngle"
                    component="0"
                    side="left"/>
        </Diagram>
       
        <Diagram name="ShoulderAdjunct" 
           column="2"
           row="1"
           xunit="% movement cycle" 
           yunit="deg"  
           diagramDescriptionDown="ext"  
           diagramDescriptionUp="int"  
           plane="f"  
           diagramType="xt" 
           diagramTitle="F  shoulder adjunct rot"> 
           <Label name="RShoulderHDAdjunctRotationAngles"
                  component="1" 
                  side="right"/>  
         </Diagram>

        <!--Diagram name="GlenohumeralAbduktion" 
           column="0"
           row="2"
           xunit="% movement cycle"
           yunit="deg" 
           diagramDescriptionDown="add" 
           diagramDescriptionUp="abd" 
           plane="f" 
           diagramType="xt" 
           diagramTitle="Glenohumeral abd/add">
           <Label name="RGlenohumeralEleDepDirCosAngle"
                  component="0" 
                  side="right"/> 
           <Label name="LGlenohumeralEleDepDirCosAngle"
                  component="0" 
                  side="left"/>
         </Diagram-->
    </Page>
    
     <Page name="Angles" rows="4" columns="3">
        
        <!-- first row -->
         
        <Diagram name="ShoulderAbduktion" 
           column="0"
           row="0"
           xunit="% movement cycle"
           yunit="deg" 
           diagramDescriptionDown="add"
           diagramDescriptionUp="abd" 
           plane="" 
           diagramType="xt" 
           diagramTitle="A  shoulder abd/add">
         <Label name="RShoulderEleDepHDCalDirCosAngle"
              component="0" 
              side="right"/>
         <Label name="LShoulderEleDepHDCalDirCosAngle"
              component="0" 
              side="left"/>       
        </Diagram>
        
        <Diagram name="ShoulderAnteRetroversion" 
           column="1"
           row="0"
           xunit="% movement cycle"
           yunit="deg" 
           diagramDescriptionDown="retro"
           diagramDescriptionUp="ante" 
           plane="" 
           diagramType="xt" 
           diagramTitle="C  shoulder ante/retro">
           <Label name="RShoulderAnteRetroHDCalDirCosAngle"
                  component="0" 
                  side="right"/>
           <Label name="LShoulderAnteRetroHDCalDirCosAngle"
                  component="0" 
                  side="left"/>
        </Diagram>
        
        <Diagram name="ShoulderIroAroGlobeAP" 
           column="2"
           row="0"
           xunit="% movement cycle"
           yunit="deg" 
           diagramDescriptionDown="ext"
           diagramDescriptionUp="int"
           plane="" 
           diagramType="xt" 
           diagramTitle="E  shoulder int/ext (globeAP) rot (HDCal)">
           <Label name="RShoulderIroAroHDCalAngleGlobeAP"
              component="0" 
              side="right"/>
           <Label name="LShoulderIroAroHDCalAngleGlobeAP"
              component="0" 
              side="left"/>        
        </Diagram>
         
        <Diagram name="HumerusIroAroGlobeAP2" 
           column="2"
           row="1"
           xunit="% movement cycle"
           yunit="deg" 
           diagramDescriptionDown="ext"
           diagramDescriptionUp="int"
           plane="" 
           diagramType="xt" 
           diagramTitle="E  shoulder int/ext (globeAP) rot">
           <Label name="RShoulderIroAroAngleGlobeAP"
              component="0" 
              side="right"/>
           <Label name="LShoulderIroAroAngleGlobeAP"
              component="0" 
              side="left"/>        
        </Diagram>

        <Diagram name="HumerusIroAroGlobe" 
           column="2"
           row="2"
           xunit="% movement cycle"
           yunit="deg" 
           diagramDescriptionDown="ext"
           diagramDescriptionUp="int"
           plane="" 
           diagramType="xt" 
           diagramTitle="E  shoulder int/ext (globe) rot">
           <Label name="RShoulderIroAroHDCalAngleGlobe"
              component="0" 
              side="right"/>
           <Label name="LShoulderIroAroHDCalAngleGlobe"
              component="0" 
              side="left"/>        
        </Diagram>
       
    </Page>
  </Pages>
      
  <!-- Gruppen von Trials z.B. schnelle und langsame Gehdurchgänge
       definieren und die zugehörigen Farben für jedweils linke und
       rechte Seite sowie die zugehörigen Normdaten -->
  <Groups>
        <DefaultGroup normData="abc.gnm"/>
  </Groups>
  
  <View>
     <Events>
          <Event name="RHS"/>
          <Event name="RTO"/>
     </Events>
     <Phases>
         <Phase name="RCycle" startEvent="RHS" endEvent="RTO"/>
     </Phases>
     <Alignment event="RHS" phase="RCycle" normalization="RCycle"/>
  </View>
  
</Sheet>
